gloss/__init__.py
gloss/gloss.py
gloss/py.typed
gloss-1.3.0.dist-info/LICENSE.txt
gloss-1.3.0.dist-info/METADATA
gloss-1.3.0.dist-info/WHEEL
gloss-1.3.0.dist-info/top_level.txt
gloss-1.3.0.dist-info/RECORD
