Metadata-Version: 2.1
Name: gloss
Version: 1.3.0
Summary: A synchronous one-to-one mapping type
Home-page: https://github.com/ucodery/gloss
Author: Jeremiah Paige
Author-email: ucodery@gmail.com
License: BSD 3-Clause License
Keywords: dict,bijective,map,mapping,collection,gloss,glossary,translation
Classifier: License :: OSI Approved :: BSD License
Classifier: Operating System :: OS Independent
Classifier: Programming Language :: Python :: 3
Classifier: Topic :: Software Development :: Libraries
Classifier: Topic :: Utilities
Requires-Python: >=3
License-File: LICENSE.txt
Provides-Extra: dev
Requires-Dist: tox ; extra == 'dev'
